[
  {
    "page": 488,
    "korean_name": "회양목명나방",
    "scientific_name": "Glyphodes perspectalis (Walker)",
    "english_name": null,
    "order_korean": "나비목",
    "order_latin": "Lepidoptera",
    "family_korean": "포충나방과",
    "family_latin": "Crambidae",
    "habitat": "공원, 아파트 주변, 도시의 길가, 산지",
    "morphology": [],
    "ecology": [],
    "other": []
  },
  {
    "page": 490,
    "korean_name": "미국흰불나방",
    "scientific_name": "Hyphantria cunea (Drury)",
    "english_name": "Fall Webworm",
    "order_korean": "나비목",
    "order_latin": "Lepidoptera",
    "family_korean": "불나방과",
    "family_latin": "Erebidae",
    "habitat": "공원, 아파트 주변, 도시의 길가, 산지",
    "morphology": [],
    "ecology": [],
    "other": []
  },
  {
    "page": 492,
    "korean_name": "독나방",
    "scientific_name": "Artaxa subflava (Bremer)",
    "english_name": null,
    "order_korean": "나비목",
    "order_latin": "Lepidoptera",
    "family_korean": "불나방과",
    "family_latin": "Erebidae",
    "habitat": "공원, 아파트 주변, 도시의 길가, 산지",
    "morphology": [],
    "ecology": [],
    "other": []
  },
  {
    "page": 494,
    "korean_name": "황다리독나방",
    "scientific_name": "Ivela auripes (Butler)",
    "english_name": null,
    "order_korean": "나비목",
    "order_latin": "Lepidoptera",
    "family_korean": "불나방과",
    "family_latin": "Erebidae",
    "habitat": "공원, 아파트 주변, 도시의 길가, 산지",
    "morphology": [],
    "ecology": [],
    "other": []
  },
  {
    "page": 496,
    "korean_name": "매미나방",
    "scientific_name": "Lymantria dispar (Linnaeus)",
    "english_name": "Gypsy Moth",
    "order_korean": "나비목",
    "order_latin": "Lepidoptera",
    "family_korean": "불나방과",
    "family_latin": "Erebidae",
    "habitat": "공원, 아파트 주변, 도시의 길가, 산지",
    "morphology": [],
    "ecology": [],
    "other": []
  },
  {
    "page": 498,
    "korean_name": "왕자팔랑나비",
    "scientific_name": "Daimio tethys (Ménétriès)",
    "english_name": null,
    "order_korean": "나비목",
    "order_latin": "Lepidoptera",
    "family_korean": "팔랑나비과",
    "family_latin": "Hesperiidae",
    "habitat": "공원, 야산, 산지",
    "morphology": [],
    "ecology": [],
    "other": []
  },
  {
    "page": 500,
    "korean_name": "멧팔랑나비",
    "scientific_name": "Erynnis montana (Bremer)",
    "english_name": null,
    "order_korean": "나비목",
    "order_latin": "Lepidoptera",
    "family_korean": "팔랑나비과",
    "family_latin": "Hesperiidae",
    "habitat": "공원, 야산, 산지",
    "morphology": [],
    "ecology": [],
    "other": []
  },
  {
    "page": 502,
    "korean_name": "줄점팔랑나비",
    "scientific_name": "Parnara guttata (Bremer & Grey)",
    "english_name": null,
    "order_korean": "나비목",
    "order_latin": "Lepidoptera",
    "family_korean": "팔랑나비과",
    "family_latin": "Hesperiidae",
    "habitat": "공원, 야산, 농가 주변",
    "morphology": [],
    "ecology": [],
    "other": []
  },
  {
    "page": 504,
    "korean_name": "푸른부전나비",
    "scientific_name": "Celastrina argiolus (Linnaeus)",
    "english_name": null,
    "order_korean": "나비목",
    "order_latin": "Lepidoptera",
    "family_korean": "부전나비과",
    "family_latin": "Lycaenidae",
    "habitat": "공원, 야산, 산지",
    "morphology": [],
    "ecology": [],
    "other": []
  },
  {
    "page": 506,
    "korean_name": "암먹부전나비",
    "scientific_name": "Cupido argiades (Pallas)",
    "english_name": null,
    "order_korean": "나비목",
    "order_latin": "Lepidoptera",
    "family_korean": "부전나비과",
    "family_latin": "Lycaenidae",
    "habitat": "공원, 야산, 산지",
    "morphology": [],
    "ecology": [],
    "other": []
  },
  {
    "page": 508,
    "korean_name": "큰주홍부전나비",
    "scientific_name": "Lycaena dispar (Haworth)",
    "english_name": null,
    "order_korean": "나비목",
    "order_latin": "Lepidoptera",
    "family_korean": "부전나비과",
    "family_latin": "Lycaenidae",
    "habitat": "공원, 야산, 습지 주변",
    "morphology": [],
    "ecology": [],
    "other": []
  },
  {
    "page": 510,
    "korean_name": "작은주홍부전나비",
    "scientific_name": "Lycaena phlaeas (Linnaeus)",
    "english_name": null,
    "order_korean": "나비목",
    "order_latin": "Lepidoptera",
    "family_korean": "부전나비과",
    "family_latin": "Lycaenidae",
    "habitat": "공원, 야산, 산지",
    "morphology": [],
    "ecology": [],
    "other": []
  },
  {
    "page": 512,
    "korean_name": "먹부전나비",
    "scientific_name": "Tongeia fischeri (Eversmann)",
    "english_name": null,
    "order_korean": "나비목",
    "order_latin": "Lepidoptera",
    "family_korean": "부전나비과",
    "family_latin": "Lycaenidae",
    "habitat": "공원, 야산, 산지",
    "morphology": [],
    "ecology": [],
    "other": []
  },
  {
    "page": 514,
    "korean_name": "흰줄표범나비",
    "scientific_name": "Argynnis laodice (Pallas)",
    "english_name": null,
    "order_korean": "나비목",
    "order_latin": "Lepidoptera",
    "family_korean": "네발나비과",
    "family_latin": "Nymphalidae",
    "habitat": "공원, 야산, 산지",
    "morphology": [],
    "ecology": [],
    "other": []
  },
  {
    "page": 516,
    "korean_name": "청띠신선나비",
    "scientific_name": "Kaniska canace (Linnaeus)",
    "english_name": null,
    "order_korean": "나비목",
    "order_latin": "Lepidoptera",
    "family_korean": "네발나비과",
    "family_latin": "Nymphalidae",
    "habitat": "공원, 야산, 산지",
    "morphology": [],
    "ecology": [],
    "other": []
  },
  {
    "page": 518,
    "korean_name": "뿔나비",
    "scientific_name": "Libythea lepita Moore",
    "english_name": null,
    "order_korean": "나비목",
    "order_latin": "Lepidoptera",
    "family_korean": "네발나비과",
    "family_latin": "Nymphalidae",
    "habitat": "공원, 야산, 산지",
    "morphology": [],
    "ecology": [],
    "other": []
  },
  {
    "page": 520,
    "korean_name": "굴뚝나비",
    "scientific_name": "Minois dryas (Scopoli)",
    "english_name": null,
    "order_korean": "나비목",
    "order_latin": "Lepidoptera",
    "family_korean": "네발나비과",
    "family_latin": "Nymphalidae",
    "habitat": "공원, 야산, 산지",
    "morphology": [],
    "ecology": [],
    "other": []
  },
  {
    "page": 522,
    "korean_name": "애기세줄나비",
    "scientific_name": "Neptis sappho (Pallas)",
    "english_name": null,
    "order_korean": "나비목",
    "order_latin": "Lepidoptera",
    "family_korean": "네발나비과",
    "family_latin": "Nymphalidae",
    "habitat": "공원, 야산, 산지",
    "morphology": [],
    "ecology": [],
    "other": []
  },
  {
    "page": 524,
    "korean_name": "네발나비",
    "scientific_name": "Polygonia c-aureum (Linnaeus)",
    "english_name": null,
    "order_korean": "나비목",
    "order_latin": "Lepidoptera",
    "family_korean": "네발나비과",
    "family_latin": "Nymphalidae",
    "habitat": "공원, 야산, 산지",
    "morphology": [],
    "ecology": [],
    "other": []
  },
  {
    "page": 526,
    "korean_name": "작은멋쟁이나비",
    "scientific_name": "Vanessa cardui (Linnaeus)",
    "english_name": "Painted Lady",
    "order_korean": "나비목",
    "order_latin": "Lepidoptera",
    "family_korean": "네발나비과",
    "family_latin": "Nymphalidae",
    "habitat": "공원, 야산, 산지",
    "morphology": [],
    "ecology": [],
    "other": []
  },
  {
    "page": 528,
    "korean_name": "큰멋쟁이나비",
    "scientific_name": "Vanessa indica (Herbst)",
    "english_name": null,
    "order_korean": "나비목",
    "order_latin": "Lepidoptera",
    "family_korean": "네발나비과",
    "family_latin": "Nymphalidae",
    "habitat": "공원, 야산, 산지",
    "morphology": [],
    "ecology": [],
    "other": []
  },
  {
    "page": 530,
    "korean_name": "도둑원뿔나방",
    "scientific_name": "Martyringa xeraula (Meyrick)",
    "english_name": null,
    "order_korean": "나비목",
    "order_latin": "Lepidoptera",
    "family_korean": "원뿔나방과",
    "family_latin": "Oecophoridae",
    "habitat": "공원, 야산, 산지",
    "morphology": [],
    "ecology": [],
    "other": []
  },
  {
    "page": 532,
    "korean_name": "사향제비나비",
    "scientific_name": "Atrophaneura alcinous (Klug)",
    "english_name": null,
    "order_korean": "나비목",
    "order_latin": "Lepidoptera",
    "family_korean": "호랑나비과",
    "family_latin": "Papilionidae",
    "habitat": "공원, 야산, 산지",
    "morphology": [],
    "ecology": [],
    "other": []
  },
  {
    "page": 534,
    "korean_name": "제비나비",
    "scientific_name": "Papilio bianor Cramer",
    "english_name": null,
    "order_korean": "나비목",
    "order_latin": "Lepidoptera",
    "family_korean": "호랑나비과",
    "family_latin": "Papilionidae",
    "habitat": "공원, 야산, 산지",
    "morphology": [],
    "ecology": [],
    "other": []
  },
  {
    "page": 536,
    "korean_name": "산제비나비",
    "scientific_name": "Papilio maackii Ménétriès",
    "english_name": null,
    "order_korean": "나비목",
    "order_latin": "Lepidoptera",
    "family_korean": "호랑나비과",
    "family_latin": "Papilionidae",
    "habitat": "공원, 야산, 산지",
    "morphology": [],
    "ecology": [],
    "other": []
  },
  {
    "page": 538,
    "korean_name": "호랑나비",
    "scientific_name": "Papilio xuthus Linnaeus",
    "english_name": null,
    "order_korean": "나비목",
    "order_latin": "Lepidoptera",
    "family_korean": "호랑나비과",
    "family_latin": "Papilionidae",
    "habitat": "공원, 야산, 산지",
    "morphology": [],
    "ecology": [],
    "other": []
  },
  {
    "page": 540,
    "korean_name": "모시나비",
    "scientific_name": "Parnassius stubbendorfii Ménétriès",
    "english_name": null,
    "order_korean": "나비목",
    "order_latin": "Lepidoptera",
    "family_korean": "호랑나비과",
    "family_latin": "Papilionidae",
    "habitat": "공원, 야산, 산지",
    "morphology": [],
    "ecology": [],
    "other": []
  },
  {
    "page": 542,
    "korean_name": "꼬리명주나비",
    "scientific_name": "Sericinus montela Gray",
    "english_name": null,
    "order_korean": "나비목",
    "order_latin": "Lepidoptera",
    "family_korean": "호랑나비과",
    "family_latin": "Papilionidae",
    "habitat": "공원, 야산, 산지",
    "morphology": [],
    "ecology": [],
    "other": []
  },
  {
    "page": 544,
    "korean_name": "노랑나비",
    "scientific_name": "Colias erate (Esper)",
    "english_name": null,
    "order_korean": "나비목",
    "order_latin": "Lepidoptera",
    "family_korean": "흰나비과",
    "family_latin": "Pieridae",
    "habitat": "공원, 야산, 산지",
    "morphology": [],
    "ecology": [],
    "other": []
  },
  {
    "page": 546,
    "korean_name": "남방노랑나비",
    "scientific_name": "Eurema mandarina (de l'Orza)",
    "english_name": null,
    "order_korean": "나비목",
    "order_latin": "Lepidoptera",
    "family_korean": "흰나비과",
    "family_latin": "Pieridae",
    "habitat": "공원, 야산, 산지",
    "morphology": [],
    "ecology": [],
    "other": []
  },
  {
    "page": 548,
    "korean_name": "각시멧노랑나비",
    "scientific_name": "Gonepteryx aspasia Ménétriès",
    "english_name": null,
    "order_korean": "나비목",
    "order_latin": "Lepidoptera",
    "family_korean": "흰나비과",
    "family_latin": "Pieridae",
    "habitat": "공원, 야산, 산지",
    "morphology": [],
    "ecology": [],
    "other": []
  },
  {
    "page": 550,
    "korean_name": "대만흰나비",
    "scientific_name": "Pieris canidia (Linnaeus)",
    "english_name": null,
    "order_korean": "나비목",
    "order_latin": "Lepidoptera",
    "family_korean": "흰나비과",
    "family_latin": "Pieridae",
    "habitat": "공원, 야산, 산지",
    "morphology": [],
    "ecology": [],
    "other": []
  },
  {
    "page": 552,
    "korean_name": "큰줄흰나비",
    "scientific_name": "Pieris melete Ménétriès",
    "english_name": null,
    "order_korean": "나비목",
    "order_latin": "Lepidoptera",
    "family_korean": "흰나비과",
    "family_latin": "Pieridae",
    "habitat": "공원, 야산, 산지",
    "morphology": [],
    "ecology": [],
    "other": []
  },
  {
    "page": 554,
    "korean_name": "배추흰나비",
    "scientific_name": "Pieris rapae (Linnaeus)",
    "english_name": "Cabbage White",
    "order_korean": "나비목",
    "order_latin": "Lepidoptera",
    "family_korean": "흰나비과",
    "family_latin": "Pieridae",
    "habitat": "공원, 야산, 산지",
    "morphology": [],
    "ecology": [],
    "other": []
  },
  {
    "page": 556,
    "korean_name": "배추좀나방",
    "scientific_name": "Plutella xylostella (Linnaeus)",
    "english_name": "Diamondback Moth",
    "order_korean": "나비목",
    "order_latin": "Lepidoptera",
    "family_korean": "집나방과",
    "family_latin": "Plutellidae",
    "habitat": "공원, 아파트 주변, 농가",
    "morphology": [],
    "ecology": [],
    "other": []
  },
  {
    "page": 558,
    "korean_name": "곡식비단명나방",
    "scientific_name": "Aglossa dimidiata (Haworth)",
    "english_name": null,
    "order_korean": "나비목",
    "order_latin": "Lepidoptera",
    "family_korean": "명나방과",
    "family_latin": "Pyralidae",
    "habitat": "주택, 창고, 농가",
    "morphology": [],
    "ecology": [],
    "other": []
  },
  {
    "page": 560,
    "korean_name": "한점쌀명나방",
    "scientific_name": "Aphomia gularis (Zeller)",
    "english_name": null,
    "order_korean": "나비목",
    "order_latin": "Lepidoptera",
    "family_korean": "명나방과",
    "family_latin": "Pyralidae",
    "habitat": "주택, 창고, 농가",
    "morphology": [],
    "ecology": [],
    "other": []
  },
  {
    "page": 562,
    "korean_name": "꿀벌부채명나방",
    "scientific_name": "Galleria mellonella (Linnaeus)",
    "english_name": "Wax Moth",
    "order_korean": "나비목",
    "order_latin": "Lepidoptera",
    "family_korean": "명나방과",
    "family_latin": "Pyralidae",
    "habitat": "양봉장, 주택, 창고",
    "morphology": [],
    "ecology": [],
    "other": []
  },
  {
    "page": 564,
    "korean_name": "화랑곡나방",
    "scientific_name": "Plodia interpunctella (Hübner)",
    "english_name": "Indian Meal Moth",
    "order_korean": "나비목",
    "order_latin": "Lepidoptera",
    "family_korean": "명나방과",
    "family_latin": "Pyralidae",
    "habitat": "주택, 창고, 농가",
    "morphology": [],
    "ecology": [],
    "other": []
  },
  {
    "page": 566,
    "korean_name": "밀가루줄명나방",
    "scientific_name": "Pyralis farinalis (Linnaeus)",
    "english_name": "Meal Moth",
    "order_korean": "나비목",
    "order_latin": "Lepidoptera",
    "family_korean": "명나방과",
    "family_latin": "Pyralidae",
    "habitat": "주택, 창고, 농가",
    "morphology": [],
    "ecology": [],
    "other": []
  },
  {
    "page": 568,
    "korean_name": "긴꼬리산누에나방",
    "scientific_name": "Actias artemis (Bremer & Grey)",
    "english_name": null,
    "order_korean": "나비목",
    "order_latin": "Lepidoptera",
    "family_korean": "산누에나방과",
    "family_latin": "Saturniidae",
    "habitat": "공원, 야산, 산지",
    "morphology": [],
    "ecology": [],
    "other": []
  },
  {
    "page": 570,
    "korean_name": "네눈박이산누에나방",
    "scientific_name": "Aglia tau (Linnaeus)",
    "english_name": null,
    "order_korean": "나비목",
    "order_latin": "Lepidoptera",
    "family_korean": "산누에나방과",
    "family_latin": "Saturniidae",
    "habitat": "공원, 야산, 산지",
    "morphology": [],
    "ecology": [],
    "other": []
  },
  {
    "page": 572,
    "korean_name": "참나무산누에나방",
    "scientific_name": "Antheraea yamamai (Guérin-Méneville)",
    "english_name": null,
    "order_korean": "나비목",
    "order_latin": "Lepidoptera",
    "family_korean": "산누에나방과",
    "family_latin": "Saturniidae",
    "habitat": "공원, 야산, 산지",
    "morphology": [],
    "ecology": [],
    "other": []
  },
  {
    "page": 574,
    "korean_name": "밤나무산누에나방",
    "scientific_name": "Caligula japonica (Moore)",
    "english_name": null,
    "order_korean": "나비목",
    "order_latin": "Lepidoptera",
    "family_korean": "산누에나방과",
    "family_latin": "Saturniidae",
    "habitat": "공원, 야산, 산지",
    "morphology": [],
    "ecology": [],
    "other": []
  },
  {
    "page": 576,
    "korean_name": "가중나무고치나방",
    "scientific_name": "Samia cynthia (Drury)",
    "english_name": null,
    "order_korean": "나비목",
    "order_latin": "Lepidoptera",
    "family_korean": "산누에나방과",
    "family_latin": "Saturniidae",
    "habitat": "공원, 야산, 산지",
    "morphology": [],
    "ecology": [],
    "other": []
  },
  {
    "page": 578,
    "korean_name": "포도박각시",
    "scientific_name": "Acosmeryx naga (Moore)",
    "english_name": null,
    "order_korean": "나비목",
    "order_latin": "Lepidoptera",
    "family_korean": "박각시과",
    "family_latin": "Sphingidae",
    "habitat": "공원, 야산, 산지",
    "morphology": [],
    "ecology": [],
    "other": []
  },
  {
    "page": 580,
    "korean_name": "머루박각시",
    "scientific_name": "Ampelophaga rubiginosa Bremer & Grey",
    "english_name": null,
    "order_korean": "나비목",
    "order_latin": "Lepidoptera",
    "family_korean": "박각시과",
    "family_latin": "Sphingidae",
    "habitat": "공원, 야산, 산지",
    "morphology": [],
    "ecology": [],
    "other": []
  },
  {
    "page": 582,
    "korean_name": "녹색박각시",
    "scientific_name": "Callambulyx tatarinovii (Bremer & Grey)",
    "english_name": null,
    "order_korean": "나비목",
    "order_latin": "Lepidoptera",
    "family_korean": "박각시과",
    "family_latin": "Sphingidae",
    "habitat": "공원, 야산, 산지",
    "morphology": [],
    "ecology": [],
    "other": []
  },
  {
    "page": 584,
    "korean_name": "콩박각시",
    "scientific_name": "Clanis bilineata (Walker)",
    "english_name": null,
    "order_korean": "나비목",
    "order_latin": "Lepidoptera",
    "family_korean": "박각시과",
    "family_latin": "Sphingidae",
    "habitat": "공원, 야산, 산지",
    "morphology": [],
    "ecology": [],
    "other": []
  },
  {
    "page": 586,
    "korean_name": "작은검은꼬리박각시",
    "scientific_name": "Macroglossum bombylans Butler",
    "english_name": null,
    "order_korean": "나비목",
    "order_latin": "Lepidoptera",
    "family_korean": "박각시과",
    "family_latin": "Sphingidae",
    "habitat": "공원, 야산, 산지",
    "morphology": [],
    "ecology": [],
    "other": []
  },
  {
    "page": 588,
    "korean_name": "벌꼬리박각시",
    "scientific_name": "Macroglossum pyrrhostictum Butler",
    "english_name": null,
    "order_korean": "나비목",
    "order_latin": "Lepidoptera",
    "family_korean": "박각시과",
    "family_latin": "Sphingidae",
    "habitat": "공원, 야산, 산지",
    "morphology": [],
    "ecology": [],
    "other": []
  },
  {
    "page": 590,
    "korean_name": "꼬리박각시",
    "scientific_name": "Macroglossum stellatarum (Linnaeus)",
    "english_name": "Hummingbird Hawk-Moth",
    "order_korean": "나비목",
    "order_latin": "Lepidoptera",
    "family_korean": "박각시과",
    "family_latin": "Sphingidae",
    "habitat": "공원, 야산, 산지",
    "morphology": [],
    "ecology": [],
    "other": []
  },
  {
    "page": 592,
    "korean_name": "뒤흰띠알락나방",
    "scientific_name": "Neochalcosia remota (Walker)",
    "english_name": null,
    "order_korean": "나비목",
    "order_latin": "Lepidoptera",
    "family_korean": "알락나방과",
    "family_latin": "Zygaenidae",
    "habitat": "공원, 야산, 산지",
    "morphology": [],
    "ecology": [],
    "other": []
  },
  {
    "page": 596,
    "korean_name": "재래꿀벌",
    "scientific_name": "Apis cerana Fabricius",
    "english_name": null,
    "order_korean": "벌목",
    "order_latin": "Hymenoptera",
    "family_korean": "꿀벌과",
    "family_latin": "Apidae",
    "habitat": "양봉장, 평지 또는 산지",
    "morphology": [
      "몸은 길쭉한 타원형이며, 일벌 기준 몸길이는 12 mm 이하로 서양꿀벌보다 다소 작고 왜소하다.",
      "전체적으로 흑갈색 바탕에 황색 털이 덮여 있으며, 검은 겹눈 사이에는 굵은 황색 털이 촘촘히 나 있다. 더듬이는 선명한 검은색이다.",
      "배는 검은색 바탕에 마디마다 황색 털이 줄지어 있어 무늬를 이룬다.",
      "다리는 흑갈색을 띠며, 뒷다리 종아리마디에는 꽃가루를 뭉쳐 운반하기 좋게 넓적한 꽃가루바구니가 발달해 있다."
    ],
    "ecology": [
      "양봉으로 기르면서, 농촌, 산지외에 최근에는 도심에서도 쉽게 관찰된다.",
      "성충은 이른 봄부터 늦가을까지 활동하며, 겨울을 제외하고 연중 활동한다.",
      "나무 속이나 바위 틈, 주택 천정 등에 집을 짓고 자생할 수 있으며, 내한성이 강해 겨울을 날 수 있다."
    ],
    "other": [
      "낭충봉아부패병으로 멸종 위기에 처했으나, 최근 저항성 신품종 보급으로 개체수가 회복되어 전국적으로 흔히 관찰된다.",
      "양봉꿀벌보다 몸색이 어둡고 배의 흰 줄무늬가 뚜렷하다. 뒷날개 특정 지점에서 시맥이 두 갈래로 갈라지는 점이 중요한 식별 기준이다."
    ]
  },
  {
    "page": 598,
    "korean_name": "양봉꿀벌",
    "scientific_name": "Apis mellifera Linnaeus",
    "english_name": "Western Honey Bee",
    "order_korean": "벌목",
    "order_latin": "Hymenoptera",
    "family_korean": "꿀벌과",
    "family_latin": "Apidae",
    "habitat": "평지 또는 산지의 여러 꽃",
    "morphology": [
      "전체적으로 길쭉한 타원형의 몸을 가졌으며, 일벌 기준 몸길이는 약 12~14 mm 내외이다.",
      "바탕색은 흑갈색이나, 그 위로 황색 또는 황갈색의 긴 털이 매우 빽빽하게 덮여 있어 본래의 바탕색이 잘 드러나지 않을 정도이다.",
      "배마디는 선명한 황색과 검은색이 교차하며 줄무늬를 형성한다. 재래꿀벌과 달리 황색 면적이 넓은 편이지만, 배 끝으로 갈수록 검은색 줄무늬가 점차 두꺼워지며 배 끝부분은 완전히 검은색을 띤다.",
      "더듬이와 다리는 검은색 또는 흑갈색을 띤다. 일벌의 뒷다리 종아리마디는 넓고 평평한 꽃가루바구니 구조로 발달해 있다."
    ],
    "ecology": [
      "마을 주변의 숲이나 들에서 벌꿀 생산을 위해 인위적으로 길러지기 때문에, 도심에서도 쉽게 관찰된다.",
      "성충은 이른 봄부터 늦가을까지 활동하며, 겨울을 제외하고 연중 활동한다.",
      "이 곤충은 식물의 꽃가루를 수집하는 과정에서 암꽃과 수꽃을 연결하여 수분을 돕는 화분매개곤충이다.",
      "대표적 사회성 곤충으로 분업화가 잘되어 있으며, 의사소통 체계가 발달했다."
    ],
    "other": [
      "우리나라 전역을 포함하여 전 세계에 분포한다.",
      "본 종은 일반적으로 재래꿀벌보다 전체적인 색이 밝고, 배마디의 검은색 줄무늬가 덜 발달되어 있다. 정확한 종의 구분은 뒷날개의 시맥 형태를 통해 이루어진다."
    ]
  },
  {
    "page": 600,
    "korean_name": "좀뒤영벌",
    "scientific_name": "Bombus ardens (Smith)",
    "english_name": null,
    "order_korean": "벌목",
    "order_latin": "Hymenoptera",
    "family_korean": "꿀벌과",
    "family_latin": "Apidae",
    "habitat": "공원, 야산, 산지, 농가 주변에서 주로 서식",
    "morphology": [
      "몸길이는 약 14~20 mm 정도로, 전체적인 몸집이 통통하고 둥근 편이다. 체색은 기본적으로 검은색이나, 암컷과 수컷의 털 색상 배열이 다르다.",
      "암컷은 온몸에 진한 흑갈색 털이 덮여 있어 어두운 인상을 준다. 제3배마디 이하에는 선명한 적갈색 털이 촘촘하게 나 있는 것이 특징이다. 개체에 따라 가슴 부위와 제1배마디 등판에 밝은색 털이 섞여 나타나기도 한다.",
      "수컷은 암컷보다 진한 적갈색 색상을 띤다. 뒷머리와 가슴, 배 부분에는 황색의 긴 털이 매우 빽빽하게 나 있어 전체적으로 노란빛을 띤다. 제4~6배마디에는 황색 털과 대비되는 주황색의 긴 털이 나 있다."
    ],
    "ecology": [
      "성충은 이른 봄인 3월부터 여름철인 7월까지 활동한다.",
      "우리나라 전역에 분포하며 제주, 서울 등 온난한 지역에서도 잘 적응하여 서식한다. 뒤영벌류 중에서도 특히 발생 시기가 빨라, 이른 봄 꽃을 찾아 날아다니는 모습을 가장 먼저 볼 수 있는 종 중 하나이다.",
      "4월경이 되면 첫 세대인 작은 크기의 일벌들이 나타나기 시작하며, 이때부터 본격적인 사회성 군집을 형성한다.",
      "사회성을 띠는 벌이지만, 가을이 되면 그해 태어난 일벌과 수벌은 모두 죽고 짝짓기를 마친 새로운 여왕벌만이 살아남는다. 이 여왕벌들은 여름철 고온기에는 활동을 멈추고 하면에 들어갔다가, 이후 겨울까지 월동을 거친 뒤 이듬해 봄에 다시 활동을 재개한다."
    ],
    "other": [
      "살충제 사용과 도시 개발에 따른 서식지 부족으로 서식 환경이 위협받고 있다. 이로 인해 도심지에서는 개체수가 점차 감소하는 추세다."
    ]
  },
  {
    "page": 602,
    "korean_name": "호박벌",
    "scientific_name": "Bombus ignitus (Smith)",
    "english_name": null,
    "order_korean": "벌목",
    "order_latin": "Hymenoptera",
    "family_korean": "꿀벌과",
    "family_latin": "Apidae",
    "habitat": "공원, 야산, 산지, 농가 주변에서 주로 서식",
    "morphology": [
      "몸길이는 17~23 mm이다.",
      "체색은 검은색이다. 암컷은 온몸에 검은색 또는 진한 흑갈색의 털이 나 있고, 제3배마디 이하는 적갈색의 털이 촘촘하게 나 있는 것이 특징이다. 개체에 따라 가슴 부위와 제1배마디 등판에 밝은색 털이 섞여 나타나기도 한다.",
      "수컷은 암컷보다 진한 적갈색 색상을 띤다. 뒷머리와 가슴, 배 부분에는 황색의 긴 털이 매우 빽빽하게 나 있어 전체적으로 노란빛을 띤다. 제4~6배마디에는 황색 털과 대비되는 주황색의 긴 털이 나 있다."
    ],
    "ecology": [
      "성충은 4~10월에 활동하며 전국 산지와 평지에 폭넓게 분포한다. 척박한 환경에서도 잘 적응하여 농작물의 화분 매개 곤충으로 활용도가 높다.",
      "4월경 월동에서 깨어난 여왕벌이 쥐굴 등 땅속이나 나무 구멍에 육아방을 만들고 홀로 산란을 시작한다. 5월부터는 첫 일벌들이 우화하여 먹이 채집과 육아를 전담하며 사회성 군집을 이룬다.",
      "가을철 짝짓기를 마친 새로운 여왕벌만 땅속에서 월동하며, 나머지 일벌과 수벌은 기온이 낮아지면 모두 사멸한다."
    ],
    "other": [
      "고온에 취약한 온대성 뒤영벌로, 기온 상승에 따른 생존 위협을 받고 있다. 이로 인해 제주도 저지대나 서울 도심 등 온난한 지역에서는 보기 어려워졌으며, 현재는 강원도 등 기온이 낮은 고산지를 중심으로 분포한다."
    ]
  },
  {
    "page": 604,
    "korean_name": "어리호박벌",
    "scientific_name": "Xylocopa appendiculata Smith",
    "english_name": "Carpenter Bee",
    "order_korean": "벌목",
    "order_latin": "Hymenoptera",
    "family_korean": "꿀벌과",
    "family_latin": "Apidae",
    "habitat": "공원, 야산, 산 가장자리, 농가 주변에서 주로 서식",
    "morphology": [
      "몸길이는 약 20 mm이다. 전체적인 바탕색은 검은색이며, 뒤영벌류와 비슷해 보이지만 배 부분에 털이 적고 매끄러운 광택이 돌아 구별된다.",
      "날개는 전체적으로 검은색을 띠지만, 빛의 각도에 따라 신비로운 보랏빛 광택이 감도는 것이 특징이다.",
      "뒷머리에서 가슴 등판까지는 밝은 황색의 털이 촘촘하게 나 있어 검은 몸체와 선명한 대비를 이룬다. 반면 가슴의 아랫면, 배, 다리에는 검은색 또는 흑갈색의 긴 털이 빽빽하게 나 있다.",
      "수컷은 머리방패와 그 위의 삼각형 무늬, 큰턱 기부의 작은 점, 그리고 더듬이 자루마디의 전면이 담황색을 띤다."
    ],
    "ecology": [
      "성충은 기온이 오르는 5월부터 늦가을인 10월까지 활발하게 활동한다. 특히 기주식물인 등나무가 개화하는 봄철에 가장 많은 개체가 관찰되는데, 이는 풍부한 꽃꿀과 꽃가루를 제공하는 등나무 꽃이 어리호박벌의 주요 먹이원이자 활동 중심지가 되기 때문이다.",
      "'목수벌(Carpenter bee)'이라 불리는 이름에 걸맞게, 죽은 식물의 줄기나 나무 조직 속에 직접 구멍을 파고 들어가 둥지를 만드는 독특한 습성을 지녔다."
    ],
    "other": [
      "도심지나 교외에서는 목조 주택의 기둥, 서까래, 목재 데크 등에 굴을 파서 집을 짓기도 하며, 이로 인해 구조물에 손상을 입히는 사례가 보고되기도 한다."
    ]
  },
  {
    "page": 606,
    "korean_name": "장미등에잎벌",
    "scientific_name": "Arge pagana (Panzer)",
    "english_name": null,
    "order_korean": "벌목",
    "order_latin": "Hymenoptera",
    "family_korean": "등에잎벌과",
    "family_latin": "Argidae",
    "habitat": "공원, 아파트 주변, 도시의 길가, 산지",
    "morphology": [
      "성충의 몸길이는 약 5~8 mm 정도이다.",
      "성충의 머리 및 가슴은 강한 광택이 감도는 깊은 남색을 띤다. 배 부분은 머리나 가슴과 대조적으로 선명한 주황색을 띠는 것이 가장 큰 특징이다. 더듬이의 채찍마디는 여러 마디로 나뉘지 않고 하나의 마디로 합쳐져 있는 구조를 보여준다. 다리는 전체적으로 노란색을 띤다.",
      "성장을 마친 유충은 몸길이가 최대 20 mm까지 자라며, 식물체 위에서 쉽게 눈에 띈다. 바탕색은 황록색이며, 몸 전체에 작은 검은색 점무늬가 조밀하게 산재해 있다.",
      "부화 초기인 어린 시기에는 검은색을 띠지만, 다 자란 성숙한 유충은 노란색으로 변한다."
    ],
    "ecology": [
      "성충은 연 3회(4~5월, 7월, 9월 상순) 발생한다. 땅속 고치에서 유충 상태로 겨울을 보낸 뒤 이듬해 봄 번데기를 거쳐 우화한다.",
      "암컷은 장미의 어린 줄기 속에 산란관을 꽂아 알을 낳는데, 이때 산란 부위가 갈라지거나 변색되는 상처가 남는다.",
      "부화한 유충은 잎 가장자리에 줄지어 모여 집단으로 식해한다. 초기에는 잎끝을 먹다가 점차 잎맥만 남기고 전체를 먹어 치워 장미와 찔레나무 등 장미속 식물의 생육에 큰 지장을 준다."
    ],
    "other": [
      "도시공원이나 주택가에 장미 식재가 많아지면서 해당 종의 발생도 증가하고 있다."
    ]
  },
  {
    "page": 608,
    "korean_name": "극동등에잎벌",
    "scientific_name": "Arge similis (Snellen van Vollenhoven)",
    "english_name": null,
    "order_korean": "벌목",
    "order_latin": "Hymenoptera",
    "family_korean": "등에잎벌과",
    "family_latin": "Argidae",
    "habitat": "공원, 아파트 주변, 도시의 길가, 산지",
    "morphology": [
      "성충의 몸길이는 5~8 mm이며, 광택이 강한 남색이며, 더듬이 채찍마디는 한 마디로 합쳐져 있고 몸 표면에는 금속 솜털로 덮여 있다.",
      "유충의 길이는 25 mm까지 자라며 연록색에 검은 점이 많이 나 있다. 머리는 어린 시기에는 검은색이나, 성숙한 유충은 노란색을 띤다."
    ],
    "ecology": [
      "보통 연 3~4회에 걸쳐 성충이 발생한다. 주요 우화 시기는 4월 하순~5월 상순을 시작으로 7월 상순, 그리고 9월 상순으로 이어진다. 기온과 환경조건에 따라 늦가을까지 추가 세대가 발생하기도 한다.",
      "성장을 마친 마지막 세대의 유충은 나무에서 내려와 땅속으로 들어가 튼튼한 고치를 짓는다. 이후 번데기가 되기 전인 유충 상태로 월동 과정을 거치며, 이듬해 봄 기온이 오르면 번데기를 거쳐 성충으로 우화한다.",
      "암컷은 잎 가장자리에 산란하며 부화된 유충이 잎 가장자리에 모여 먹이를 먹는다.",
      "진달래, 철쭉, 영산홍 등 진달래과 식물의 잎을 먹는다."
    ],
    "other": [
      "도시공원이나 주택가에 철쭉과 영산홍 식재가 많아지면서 해당 종의 발생도 증가하고 있다."
    ]
  },
  {
    "page": 610,
    "korean_name": "나나니",
    "scientific_name": "Ammophila infesta Smith",
    "english_name": null,
    "order_korean": "벌목",
    "order_latin": "Hymenoptera",
    "family_korean": "구멍벌과",
    "family_latin": "Sphecidae",
    "habitat": "공원, 야산, 산 가장자리, 농가 주변에서 주로 서식",
    "morphology": [
      "몸길이는 20~25 mm이며, 전체적으로 매우 가늘고 길쭉하다.",
      "가슴에는 점각이 빽빽하여 표면이 거칠며, 나나니류 특유의 실처럼 가느다란 두 마디의 배자루가 발달해 있다.",
      "암컷은 몸 전체가 검은색이며 배 부분에 은은한 남색 광택이 감돈다. 반면 수컷은 암컷보다 더 가늘고 적갈색을 띠며, 등 중앙에 검은색 세로무늬가 있어 쉽게 구별된다."
    ],
    "ecology": [
      "성충은 5~10월에 활동하며, 산길이나 들판 등 햇볕이 잘 드는 개활지에서 흔히 발견된다.",
      "땅속에 직접 굴을 파거나 기존 구멍을 활용해 새끼를 기르는 단독성 사냥벌이다.",
      "주로 나비목 유충을 사냥하며, 독침으로 유충의 신경마디를 찔러 마취시킨다. 이는 먹이가 부패하지 않고 신선한 상태를 유지하게 하여 부화한 새끼에게 공급하기 위함이다.",
      "마취된 유충을 둥지로 끌고 들어온 뒤 그 몸 위에 알을 낳는다. 부화한 나나니 유충은 둥지 내에 비축된 신선한 먹이를 먹으며 성장한다."
    ],
    "other": [
      "농작물에 피해를 주는 다양한 나방류 유충을 사냥하므로, 농업 및 산림 생태계에서 해충의 밀도를 조절하는 중요한 천적 자원으로 평가받는다."
    ]
  },
  {
    "page": 612,
    "korean_name": "개나리잎벌",
    "scientific_name": "Apareophora forsythiae Sato",
    "english_name": null,
    "order_korean": "벌목",
    "order_latin": "Hymenoptera",
    "family_korean": "잎벌과",
    "family_latin": "Tenthredinidae",
    "habitat": "공원, 아파트 주변, 도시의 길가, 산지",
    "morphology": [
      "성충의 다리는 노란색이다.",
      "유충의 길이는 16 mm 정도이며, 통통하고 검은 몸에 짧고 하얀 털이 빽빽하게 나 있다."
    ],
    "ecology": [
      "성충은 4월에 출현하여 개나리 잎에 알을 낳는다.",
      "성충의 출현 기간이 일주일 정도로 매우 짧아 관찰이 어려우나, 유충은 한 달 정도의 기간 동안 무리를 지어 개나리에 붙어 있으므로 도심에서 쉽게 볼 수 있다.",
      "개나리의 해충이다. 봄에 여러 마리의 유충이 모여서 개나리의 잎을 줄기만 앙상하게 남을 때까지 먹어 치우므로 피해를 받은 나무는 발육에 영향을 받고 경관상으로도 보기 좋지 않다.",
      "다 자란 유충은 땅으로 내려와서 1 cm 정도의 깊이로 집을 짓고 들어가 월동한다."
    ],
    "other": [
      "도시공원이나 길가에 개나리 식재가 많아지면서 해당 종의 발생도 증가하고 있다."
    ]
  },
  {
    "page": 614,
    "korean_name": "큰호리병벌",
    "scientific_name": "Oreumenes decoratus (Smith)",
    "english_name": null,
    "order_korean": "벌목",
    "order_latin": "Hymenoptera",
    "family_korean": "말벌과",
    "family_latin": "Vespidae",
    "habitat": "공원, 아파트 주변, 산 가장자리, 숲길",
    "morphology": [
      "몸길이는 25~30 mm로, 호리병벌류 중 대형종에 속한다. 검은색 바탕에 머리부터 배까지 황색 및 황갈색 무늬가 복잡하게 발달해 있다.",
      "머리방패와 더듬이 기부, 겹눈 뒷가두리는 짙은 황색을 띤다.",
      "가슴 부위와 전신복절 곳곳에 선명한 황갈색 무늬가 있으며, 제1·2배마디 뒷가두리에도 황갈색 띠무늬가 있다. 특히 제1배마디는 호리병 입구처럼 길고 가늘게 발달하였다.",
      "머리와 가슴, 배자루 표면에는 점각이 많아 질감이 거칠다."
    ],
    "ecology": [
      "성충은 6~10월에 활발히 활동하며, 민가나 도심공원 등 인간 거주지 인근에서 자주 관찰된다. 이는 집을 짓기 위한 벽면과 먹이원이 풍부하기 때문이다.",
      "암컷은 젖은 흙을 이용해 벽면이나 식물 줄기에 정교한 호리병 모양의 둥지를 만든다. 둥지가 완성되면 나비목 유충을 마취시켜 방 안에 채워 넣고, 천장에 알을 하나씩 낳아 매단 뒤 입구를 봉인한다.",
      "부화한 유충은 어미가 비축한 신선한 먹이를 먹으며 자라며, 성충은 주로 꽃을 찾아 꽃꿀을 섭취한다."
    ],
    "other": []
  },
  {
    "page": 616,
    "korean_name": "큰뱀허물쌍살벌",
    "scientific_name": "Parapolybia crocea Saito-Morooka, Nguyen & Kojima",
    "english_name": null,
    "order_korean": "벌목",
    "order_latin": "Hymenoptera",
    "family_korean": "말벌과",
    "family_latin": "Vespidae",
    "habitat": "공원, 숲 가장자리, 산지",
    "morphology": [
      "몸길이는 12~25 mm이며, 유사종인 뱀허물쌍살벌보다 몸집이 크다. 황갈색 바탕에 검은 무늬가 적고 연해 전체적으로 매우 밝은 노란색을 띤다.",
      "머리방패에 검은 세로선이 없는 것이 특징이며, 암컷은 머리방패의 폭이 넓어 가로로 퍼진 형태다.",
      "제1배마디가 잎자루처럼 길게 늘어나 허리가 매우 가늘어 보인다.",
      "날개는 투명하나 앞 가장자리는 황갈색을 띤다.",
      "수컷은 더듬이 끝마디가 매우 가늘고 길게 발달하여, 바로 앞마디보다 2배 이상 긴 것이 특징이다."
    ],
    "ecology": [
      "성충은 봄부터 늦가을까지 전국의 산지와 숲 주변에서 흔히 관찰된다.",
      "계급에 따라 분업화된 사회성 군집 생활을 하며, 봄철 홀로 둥지를 짓기 시작한 여왕벌은 여름 이후 세력이 안정되면 새로운 여왕벌과 수벌을 생산한다.",
      "가을철 짝짓기를 마친 새로운 여왕벌만 월동하고 나머지 개체들은 사멸하며 군집이 해체된다.",
      "육식성으로 나비목 유충 등을 사냥해 경단 형태로 만들어 새끼에게 먹이며, 성충은 주로 꽃꿀이나 수액을 섭취한다.",
      "이름처럼 뱀의 허물과 같이 길쭉하고 넓적한 형태의 집을 나뭇가지나 잎 뒷면에 매달아 짓는 것이 특징이다."
    ],
    "other": []
  },
  {
    "page": 618,
    "korean_name": "뱀허물쌍살벌",
    "scientific_name": "Parapolybia varia (Fabricius)",
    "english_name": null,
    "order_korean": "벌목",
    "order_latin": "Hymenoptera",
    "family_korean": "말벌과",
    "family_latin": "Vespidae",
    "habitat": "공원, 숲 가장자리, 산지",
    "morphology": [
      "몸길이는 15~22 mm로, 유사종인 큰뱀허물쌍살벌보다 다소 작다.",
      "황적갈색 바탕에 진한 암갈색 줄무늬가 많아 전체적으로 어두운 인상을 준다.",
      "머리와 가슴 표면은 평활하지만 광택이 거의 없으며, 암컷과 일벌의 황색 머리방패 중앙에는 선명한 암갈색 세로무늬가 있다.",
      "가슴 옆면의 줄무늬가 매우 진하고 명확하다. 전신복절은 황색이나 중앙의 세로 도랑과 기부의 무늬 2개는 짙은 암갈색을 띠어 대조를 이룬다."
    ],
    "ecology": [
      "성충은 봄부터 늦가을까지 활동한다. 사회성 곤충으로, 월동을 마친 여왕벌이 봄에 둥지를 짓기 시작해 일벌을 늘려가며, 이후 새로운 여왕벌과 수벌을 생산해 번식한다.",
      "식물 섬유와 침을 섞어 종이 재질의 둥지를 짓는데, 이름처럼 뱀의 허물과 같이 가늘고 길쭉한 형태를 띤다. 주로 나뭇가지나 잎 뒷면, 인가의 처마 아래에 둥지를 매달아 만든다.",
      "유충에게는 사냥한 나비목 유충 등을 경단 모양으로 뭉쳐 먹이며, 성충은 주로 꽃꿀이나 수액을 섭취하며 에너지를 얻는다."
    ],
    "other": []
  },
  {
    "page": 620,
    "korean_name": "어리별쌍살벌",
    "scientific_name": "Polistes nipponensis Pérez",
    "english_name": null,
    "order_korean": "벌목",
    "order_latin": "Hymenoptera",
    "family_korean": "말벌과",
    "family_latin": "Vespidae",
    "habitat": "공원, 숲 가장자리, 산지 덤불",
    "morphology": [
      "몸길이는 약 18 mm 내외이며, 몸의 전체적인 바탕색은 적갈색이다.",
      "앞가슴과 작은방패판의 가장자리에는 선명한 노란색 무늬가 있어 적갈색 바탕과 대비를 이룬다. 배 부분은 제2마디부터 제4마디까지 황갈색 띠가 둘러져 있다. 다리의 종아리마디와 발목마디 또한 몸색과 유사한 적갈색을 띤다.",
      "머리방패의 형태를 보면 가로폭과 세로폭의 길이가 거의 비슷하여 정사각형에 가까운 모양을 하고 있다.",
      "둥지 내부에서 유충이 성장을 마치고 번데기가 되기 위해 짓는 고치의 덮개 색상이 노란색을 띤다."
    ],
    "ecology": [
      "성충은 봄부터 가을까지 만날 수 있다.",
      "사회성 곤충으로 여왕개체가 월동 후 둥지를 만들기 시작하여 일벌 개체수가 증식되면 여왕과 숫벌을 생산하여 번식한다.",
      "짝짓기를 마친 새 여왕벌은 나무 구멍, 창문틀, 바위틈 등 따뜻한 곳을 찾아 월동한다.",
      "다른 곤충을 사냥하여 유충 먹이로 이용하며, 도심공원이나 숲 가장자리에서 서식한다."
    ],
    "other": [
      "방제 활동으로 인해 해당 종의 발생량이 점차 감소하는 추세이다.",
      "과거에는 큰별쌍살벌과 혼용하여 불리기도 했다."
    ]
  },
  {
    "page": 622,
    "korean_name": "왕바다리",
    "scientific_name": "Polistes rothneyi Cameron",
    "english_name": null,
    "order_korean": "벌목",
    "order_latin": "Hymenoptera",
    "family_korean": "말벌과",
    "family_latin": "Vespidae",
    "habitat": "공원, 숲 가장자리, 산지 건물 주변",
    "morphology": [
      "몸길이는 약 25 mm 내외로, 우리나라에 서식하는 쌍살벌류 중 가장 몸집이 큰 대형종이다.",
      "몸의 색상과 무늬는 개체나 지역에 따른 변이가 매우 심한 편이다. 일반적으로는 검은색 바탕 위에 황갈색 또는 적갈색의 복잡한 무늬가 조화롭게 배치되어 있다.",
      "암컷은 머리 뒷부분의 뒷머리용골선이 큰턱의 기부까지 끊어지지 않고 완전하게 이어져 있는 것이 특징이다.",
      "수컷은 겹눈과 머리방패가 서로 맞붙어 있는 형태를 취하고 있어, 이 두 부위가 떨어져 있는 유사종인 등검정쌍살벌과 명확히 구분된다."
    ],
    "ecology": [
      "성충은 이른 봄인 3월부터 늦가을인 11월까지 관찰되어, 쌍살벌류 중에서도 활동 기간이 매우 긴 편에 속한다.",
      "사회성 곤충으로 여왕개체가 월동 후 둥지를 만들기 시작하여 일벌 개체수가 증식되면 여왕과 숫벌을 생산하여 번식한다.",
      "짝짓기를 마친 새 여왕벌은 나무 구멍, 창문틀, 바위틈 등 따뜻한 곳을 찾아 월동한다.",
      "다른 곤충을 사냥하여 유충 먹이로 이용하며, 도심공원이나 숲 가장자리에서 서식하며 건물 처마에 집짓기를 좋아한다."
    ],
    "other": [
      "방제 활동으로 인해 해당 종의 발생량이 점차 감소하는 추세이다."
    ]
  },
  {
    "page": 624,
    "korean_name": "좀말벌",
    "scientific_name": "Vespa analis Fabricius",
    "english_name": null,
    "order_korean": "벌목",
    "order_latin": "Hymenoptera",
    "family_korean": "말벌과",
    "family_latin": "Vespidae",
    "habitat": "공원, 숲 가장자리, 산지",
    "morphology": [
      "몸길이는 22~31 mm로, 말벌류 중 소형종에 속한다. 검은색 바탕의 몸과 대비되는 붉은빛 머리가 시각적인 특징이다.",
      "머리는 전체적으로 적갈색이며 이마방패는 더 짙은 갈색을 띤다. 특히 3개의 홑눈 주변에 검은색 점각이 밀집해 있어 검은 점처럼 보인다.",
      "가슴 부위는 무늬 없이 전체적으로 검은색이다.",
      "배마디마다 직선형의 노란색 띠무늬가 있다. 제2배마디 기부에는 붉은색 무늬가 섞이는 등 개체에 따라 색 변이가 나타나기도 하며, 갈색 타원 무늬가 노란색 띠 부위로 침범하여 형태가 변형되기도 한다."
    ],
    "ecology": [
      "성충은 봄철인 4월부터 늦가을인 11월까지 관찰된다.",
      "사회성 곤충으로 여왕 개체가 월동 후 둥지를 만들기 시작하여 일벌 개체수가 증식되면 여왕과 수벌을 생산하여 번식한다.",
      "짝짓기를 마친 새 여왕벌은 나무 구멍, 낙엽 밑, 바위틈 등 온도가 일정한 곳을 찾아 월동한다.",
      "강한 포식성을 지닌 육식성 곤충으로, 나비목의 유충이나 파리류 등 다른 곤충을 사냥하여 유충의 먹이로 이용한다."
    ],
    "other": [
      "주로 도시공원이나 덤불 속에 집을 짓는 경우가 많아, 벌쏘임 사고의 위험이 높다. 방제로 인해 도심과 주택가에서의 발생 빈도는 점차 줄어드는 추세다."
    ]
  },
  {
    "page": 626,
    "korean_name": "말벌",
    "scientific_name": "Vespa crabro Linnaeus",
    "english_name": "European Hornet",
    "order_korean": "벌목",
    "order_latin": "Hymenoptera",
    "family_korean": "말벌과",
    "family_latin": "Vespidae",
    "habitat": "공원, 숲 가장자리, 산지",
    "morphology": [
      "몸길이는 19~28 mm이다. 흑갈색 바탕에 배를 중심으로 황갈색과 적갈색 무늬가 어우러져 있다.",
      "머리는 황갈색이지만 정수리의 홑눈 주변에는 특징적인 마름모꼴 흑갈색 무늬가 있다. 이마방패는 가장자리가 검고 표면에 큰 점각이 빽빽하게 나 있다.",
      "배마디 뒷가두리마다 선명한 황갈색 띠무늬가 있다. 제1배마디의 띠는 폭이 좁지만, 제2배마디부터는 폭이 넓어지며 직선이 아닌 굽이치는 물결무늬 형태를 띠는 것이 특징이다."
    ],
    "ecology": [
      "성충은 4~10월에 활동한다. 월동에서 깬 여왕벌이 홀로 첫 세대 일벌을 길러내며, 군집이 안정되면 산란에만 전념한다.",
      "규모가 정점에 달하는 가을철에 새로운 여왕벌과 수벌을 생산하며, 짝짓기를 마친 새로운 여왕벌만 나무 구멍이나 바위틈 등에서 월동한다.",
      "폐쇄된 공간을 선호하여, 나무 구멍 속이나 건물 천장, 벽면 내부 등 어둡고 밀폐된 곳에 둥지를 트는 습성이 강하다.",
      "강한 육식성을 띠어 나비목 유충 등을 사냥해 말벌 유충의 먹이로 삼는다."
    ],
    "other": [
      "벌쏘임 사고가 빈번히 발생하며, 방제로 인해 도심과 주택가에서의 발생 빈도는 점차 줄어드는 추세다."
    ]
  },
  {
    "page": 628,
    "korean_name": "검정말벌",
    "scientific_name": "Vespa dybowskii André",
    "english_name": null,
    "order_korean": "벌목",
    "order_latin": "Hymenoptera",
    "family_korean": "말벌과",
    "family_latin": "Vespidae",
    "habitat": "공원, 숲 가장자리, 산지",
    "morphology": [
      "몸길이는 약 19~28 mm 정도로, 말벌속 내에서는 소형 내지 중형에 속하는 종이다.",
      "다른 말벌류와 달리 배마디에 노란색 띠무늬가 거의 없고 전신이 매우 어두운 색조를 띠어 한눈에 구별된다.",
      "배마디 등판은 뒷가두리에 아주 얇게 나타나는 암갈색 띠를 제외하면 완전히 검은색이다.",
      "이마방패 앞가두리의 중앙 함입 부위가 깊게 패어 있으며, 양옆의 돌출부는 반원형에 가깝다. 어깨판 앞쪽에 위치한 용골선이 뚜렷하게 발달해 있다."
    ],
    "ecology": [
      "성충은 4월부터 10월까지 활동한다.",
      "사회성 곤충으로 여왕개체가 월동 후 털보말벌이나 말벌의 둥지에 침입해 여왕을 죽이고 둥지를 점령한다. 점령당한 말벌 일벌은 검정말벌의 알과 유충을 돌보며 키운다. 숙주 말벌은 자연히 줄어들면서 검정말벌의 개체수가 증가하면 여왕과 수벌을 생산하여 번식한다.",
      "짝짓기를 마친 새 여왕벌은 나무 구멍, 낙엽 밑, 바위틈 등 온도가 일정한 곳을 찾아 월동한다.",
      "다른 곤충을 사냥하여 유충 먹이로 이용하며, 도심공원이나 숲 가장자리, 산지에서 서식하며 나무 구멍, 건물 속에 서식한다."
    ],
    "other": [
      "벌쏘임 사고가 빈번히 발생하며, 방제로 인해 도심과 주택가에서의 발생 빈도는 점차 줄어드는 추세다."
    ]
  },
  {
    "page": 630,
    "korean_name": "장수말벌",
    "scientific_name": "Vespa mandarinia Smith",
    "english_name": "Asian Giant Hornet",
    "order_korean": "벌목",
    "order_latin": "Hymenoptera",
    "family_korean": "말벌과",
    "family_latin": "Vespidae",
    "habitat": "공원, 숲 가장자리, 산지",
    "morphology": [
      "몸길이는 약 27~44 mm에 달하며, 말벌류 중 세계에서 가장 큰 대형종이다.",
      "몸 표면은 기본적으로 갈색을 띠며, 뒷머리와 가슴에는 갈색 털이, 배 부분에는 황갈색의 긴 털이 성글게 나 있다.",
      "머리 전체는 선명한 황적갈색을 띠지만, 3개의 홑눈 부근과 강력한 큰턱의 끝부분은 흑갈색을 띤다.",
      "각 배마디의 등판과 배판 뒷가두리에는 선명한 황갈색 띠무늬가 둘러져 있다. 특히 배의 끝부분인 꼬리마디는 거의 전체가 황갈색을 띤다."
    ],
    "ecology": [
      "성충은 4월부터 11월까지 활동한다.",
      "사회성 곤충으로 여왕개체가 월동 후 둥지를 만들기 시작하여 일벌 개체수가 증식되면 여왕과 수벌을 생산하여 번식한다. 일벌의 개체수가 증가하면 여왕과 수벌을 생산하여 번식한다.",
      "짝짓기를 마친 새 여왕벌은 나무 구멍, 낙엽 밑, 바위틈 등 온도가 일정한 곳을 찾아 월동한다.",
      "다른 곤충을 사냥하여 유충 먹이로 이용하며, 도심공원이나 숲 가장자리, 산지에서 서식하며 주로 나무 속의 빈 공간, 인가의 벽이나 추녀 밑에 둥글고 큰 둥지를 만든다."
    ],
    "other": [
      "매우 공격적이며, 사람을 만나도 피하지 않고 공격한다. 숲속 큰 나무 부근에서 벌 쏘임 사고가 잘 일어난다."
    ]
  },
  {
    "page": 632,
    "korean_name": "등검은말벌",
    "scientific_name": "Vespa velutina Lepeletier",
    "english_name": null,
    "order_korean": "벌목",
    "order_latin": "Hymenoptera",
    "family_korean": "말벌과",
    "family_latin": "Vespidae",
    "habitat": "야산이나 도심의 민가 주변에서 주로 서식",
    "morphology": [
      "일벌의 크기는 22~25 mm이다.",
      "국내 말벌종류와 차이점은 앞가슴등판 측면 아래부위에 몇 개의 용골선이 있으며 등판 전체와 머리 뒷부분이 완전히 흑색인 것으로 구분한다."
    ],
    "ecology": [
      "월동을 마친 여왕벌은 봄철인 4~5월경에 나타나 둥지를 틀기 시작한다. 군집의 활동이 가장 왕성한 시기는 8~9월이며, 10월 중순까지도 도심 및 산지에서 빈번하게 출현한다.",
      "개체수가 최고 3,000여 마리에 달할 정도로 대규모 군집을 형성한다. 한 해 동안 벌집 하나에서 배출되는 성충의 수는 약 15,000여 마리에 이를 만큼 번식력이 폭발적이다.",
      "토종 말벌의 집보다 2~3배 정도 큰 대형 둥지를 짓는다. 위치를 가리지 않고 나무 꼭대기, 건물의 처마 밑, 관목 덤불 속, 심지어 땅속까지 다양한 장소에 집을 짓는 뛰어난 적응력을 보인다.",
      "유충은 성충이 사냥해온 꿀벌 종류 및 야생 곤충을 가리지 않고 포식한다."
    ],
    "other": [
      "2003년 유입된 이후 중국 무역선을 통해 부산으로 들어온 것으로 추정되며, 약 10년 만에 빠르게 전국으로 확산되었다.",
      "2019년 생태계교란생물로 지정되어 관리되고 있으며, 꿀벌을 포식하는 양봉 해충으로서 농가에 큰 피해를 주고 있다."
    ]
  },
  {
    "page": 634,
    "korean_name": "땅벌",
    "scientific_name": "Vespula flaviceps (Smith)",
    "english_name": null,
    "order_korean": "벌목",
    "order_latin": "Hymenoptera",
    "family_korean": "말벌과",
    "family_latin": "Vespidae",
    "habitat": "공원, 숲 가장자리, 산지",
    "morphology": [
      "성충의 몸길이는 8~20 mm이며, 소형종이다. 몸은 검은색이나 황색 무늬가 전체적으로 산재해 있으며 무늬 변이가 심하다.",
      "머리는 장방형이고, 정수리의 길이는 겹눈 사이 간격보다도 좁다. 이마는 가는 점각과 검은색으로 긴 털이 많이 나 있다.",
      "각 배마디무늬는 직선형으로 되어 있으나 변이가 심하여 물결무늬가 있기도 하다."
    ],
    "ecology": [
      "성충은 5월부터 11월까지 활동한다.",
      "사회성 곤충으로 여왕개체가 월동 후 둥지를 만들기 시작하여 일벌 개체수가 증식되면 여왕과 수벌을 생산하여 번식한다.",
      "짝짓기를 마친 새 여왕벌은 나무 구멍, 낙엽 밑, 바위틈 등 따뜻한 곳을 찾아 월동한다.",
      "다른 곤충을 사냥하여 유충 먹이로 이용하며, 도심공원이나 숲 가장자리, 산지에서 서식하며 땅속에 집을 짓는다."
    ],
    "other": [
      "땅벌집을 인지하지 못한 채 밟아 쏘이는 사고가 빈번하며, 방제 강화로 인해 발생이 감소하는 추세이다."
    ]
  },
  {
    "page": 636,
    "korean_name": "참땅벌",
    "scientific_name": "Vespula koreensis (Radoszkowski)",
    "english_name": null,
    "order_korean": "벌목",
    "order_latin": "Hymenoptera",
    "family_korean": "말벌과",
    "family_latin": "Vespidae",
    "habitat": "공원, 숲 가장자리, 산지",
    "morphology": [
      "몸길이는 약 8~20 mm 정도로, 말벌과 내에서는 소형종에 속한다.",
      "검은색 바탕에 선명한 황색 무늬가 몸 전체에 조밀하게 산재해 있다. 이 노란 무늬는 개체나 지역에 따른 변이가 상당히 심한 편이다.",
      "뒤쪽 홑눈의 뒷가두리가 겹눈의 뒷가두리 선상과 거의 일렬로 위치한다. 뒷머리용골선은 큰턱의 기부까지 끊어지지 않고 완전하며 뚜렷하게 발달해 있다.",
      "첫 번째 배마디 표면에 흔적적인 융기선들이 조밀하게 나타난다.",
      "땅벌에 비해 노란색 띠무늬가 훨씬 넓고 선명하다. 가슴 옆판에 나타나는 노란색 무늬의 면적이 훨씬 넓고 개수가 많다."
    ],
    "ecology": [
      "성충은 4월부터 11월까지 활동한다.",
      "사회성 곤충으로 여왕개체가 월동 후 둥지를 만들기 시작하여 일벌 개체수가 증식되면 여왕과 수벌을 생산하여 번식한다.",
      "짝짓기를 마친 새 여왕벌은 나무 구멍, 낙엽 밑, 바위틈 등 따뜻한 곳을 찾아 월동한다.",
      "다른 곤충을 사냥하여 유충 먹이로 이용하며, 도심공원이나 숲 가장자리, 산지에서 서식하며 땅속에 주로 집을 짓는다."
    ],
    "other": [
      "벌집의 존재를 인지하지 못하고 밟아 벌쏘임 사고가 빈번하게 발생한다."
    ]
  }
]
