{
  "generatedAt": "2026-05-21T07:47:08.025Z",
  "source": "국립생물자원관 KTSN API /gwsvc/openapi/rest/ktsn/taxons/search?schTxgrpGroupCd=IN",
  "order": {
    "id": "diptera",
    "scientificName": "Diptera",
    "commonName": "파리목",
    "orderKtsn": 120000020933,
    "abstract": "파리목(Diptera)은 파리, 모기, 등에 등이 속해 있는 곤충의 한 분류이다. 수십 개의 과에 85,000여 종이 있다. 대한민국에서 발견하여 기록한 전체기록 종은 1,099종이다. 작거나 중간 크기의 곤충으로서, 형태와 습성이 매우 다양하다. 머리부에는 발달된 겹눈이 있으며, 입은 찌르는형·씹는형·핥는형 등이 있고, 다양한 촉각을 갖는다. 특히 앞날개가 발달하여 있으며, 맥은 적으나 나는 힘은 강하다. 뒷날개는 변형되어 평형을 유지하는 기관인 평형곤이 되었다. 날개가 퇴화된 것도 많다. 완전변태를 하며, 유충은 애벌래 형태를 띈다. 파리는 우리 주위에서 쉽게 볼 수 있지만, 바다에서 생활하는 종류도 있다. 모기·깔따구·등에·파리매·똥파리·초파리·집파리·쇠파리·쉬파리·각다귀 등이 이에 포함된다.",
    "description": "파리목(Diptera)은 파리, 모기, 등에 등이 속해 있는 곤충의 한 분류이다. 수십 개의 과에 85,000여 종이 있다. 대한민국에서 발견하여 기록한 전체기록 종은 1,099종이다. 작거나 중간 크기의 곤충으로서, 형태와 습성이 매우 다양하다. 머리부에는 발달된 겹눈이 있으며, 입은 찌르는형·씹는형·핥는형 등이 있고, 다양한 촉각을 갖는다. 특히 앞날개가 발달하여 있으며, 맥은 적으나 나는 힘은 강하다. 뒷날개는 변형되어 평형을 유지하는 기관인 평형곤이 되었다. 날개가 퇴화된 것도 많다. 완전변태를 하며, 유충은 애벌래 형태를 띈다. 파리는 우리 주위에서 쉽게 볼 수 있지만, 바다에서 생활하는 종류도 있다. 모기·깔따구·등에·파리매·똥파리·초파리·집파리·쇠파리·쉬파리·각다귀 등이 이에 포함된다."
  },
  "family": {
    "id": "rhagionidae",
    "scientificName": "Rhagionidae",
    "commonName": "노랑등에과",
    "familyKtsn": 120000022685
  },
  "speciesCount": 5,
  "insects": [
    {
      "ktsn": 120000225277,
      "scientificName": "Chrysopilus dives Loew, 1872",
      "commonName": "찬노랑등에",
      "terminalLatinName": "dives",
      "nomenclaturalAuthor": "Loew",
      "namingYear": "1872",
      "corsynSeYn": "Y",
      "egspcsYn": "N",
      "hrmflSpecsYn": "N",
      "dispYn": "N",
      "phspYn": "N",
      "korUnqBispYn": "N",
      "ntmYn": "N",
      "taxonomy": {
        "phylum": {
          "scientificName": "Arthropoda",
          "commonName": "절지동물문",
          "ktsn": 120000013748
        },
        "class": {
          "scientificName": "Insecta",
          "commonName": "곤충강",
          "ktsn": 120000013749
        },
        "order": {
          "scientificName": "Diptera",
          "commonName": "파리목",
          "ktsn": 120000020933
        },
        "family": {
          "scientificName": "Rhagionidae",
          "commonName": "노랑등에과",
          "ktsn": 120000022685
        },
        "genus": {
          "scientificName": "Chrysopilus",
          "commonName": "",
          "ktsn": 120000022686
        },
        "subgenus": {
          "scientificName": "",
          "commonName": "",
          "ktsn": null
        },
        "species": {
          "scientificName": "dives",
          "commonName": "찬노랑등에",
          "ktsn": 120000225277
        }
      },
      "digitalContent": {
        "cachedAt": "2026-05-21T09:17:27.013Z",
        "source": "https://species.nibr.go.kr/gwsvc/openapi/rest/digital/bispconts/search",
        "totalElements": 0,
        "totalPages": 1,
        "thumbnailUrl": null,
        "thumbnail": null,
        "contents": {
          "EO": [],
          "FR": [],
          "DT": [],
          "EX": []
        }
      },
      "eol": {
        "pageId": 819293,
        "canonical": "Chrysopilus dives",
        "fetchedAt": "2026-05-24T09:07:23.097Z",
        "vernaculars": {
          "ko": [],
          "en": [],
          "ja": []
        },
        "habitat": [],
        "geographic": [],
        "introduced": [],
        "eats": [],
        "visitsFlowersOf": [],
        "pathogenOf": [],
        "gbifRecords": 1
      }
    },
    {
      "ktsn": 120000507407,
      "scientificName": "Chrysopilus peninsularis Lee and Suh, 2022",
      "commonName": "반도노랑등에",
      "terminalLatinName": "peninsularis",
      "nomenclaturalAuthor": "Lee and Suh",
      "namingYear": "2022",
      "corsynSeYn": "Y",
      "egspcsYn": "N",
      "hrmflSpecsYn": "N",
      "dispYn": "N",
      "phspYn": "N",
      "korUnqBispYn": "Y",
      "ntmYn": "N",
      "taxonomy": {
        "phylum": {
          "scientificName": "Arthropoda",
          "commonName": "절지동물문",
          "ktsn": 120000013748
        },
        "class": {
          "scientificName": "Insecta",
          "commonName": "곤충강",
          "ktsn": 120000013749
        },
        "order": {
          "scientificName": "Diptera",
          "commonName": "파리목",
          "ktsn": 120000020933
        },
        "family": {
          "scientificName": "Rhagionidae",
          "commonName": "노랑등에과",
          "ktsn": 120000022685
        },
        "genus": {
          "scientificName": "Chrysopilus",
          "commonName": "",
          "ktsn": 120000022686
        },
        "subgenus": {
          "scientificName": "",
          "commonName": "",
          "ktsn": null
        },
        "species": {
          "scientificName": "peninsularis",
          "commonName": "반도노랑등에",
          "ktsn": 120000507407
        }
      },
      "digitalContent": {
        "cachedAt": "2026-05-21T09:17:27.013Z",
        "source": "https://species.nibr.go.kr/gwsvc/openapi/rest/digital/bispconts/search",
        "totalElements": 0,
        "totalPages": 1,
        "thumbnailUrl": null,
        "thumbnail": null,
        "contents": {
          "EO": [],
          "FR": [],
          "DT": [],
          "EX": []
        }
      }
    },
    {
      "ktsn": 120000022687,
      "scientificName": "Chrysopilus sauteri Bezzi, 1907",
      "commonName": "노랑등에",
      "terminalLatinName": "sauteri",
      "nomenclaturalAuthor": "Bezzi",
      "namingYear": "1907",
      "corsynSeYn": "Y",
      "egspcsYn": "N",
      "hrmflSpecsYn": "N",
      "dispYn": "N",
      "phspYn": "N",
      "korUnqBispYn": "N",
      "ntmYn": "N",
      "taxonomy": {
        "phylum": {
          "scientificName": "Arthropoda",
          "commonName": "절지동물문",
          "ktsn": 120000013748
        },
        "class": {
          "scientificName": "Insecta",
          "commonName": "곤충강",
          "ktsn": 120000013749
        },
        "order": {
          "scientificName": "Diptera",
          "commonName": "파리목",
          "ktsn": 120000020933
        },
        "family": {
          "scientificName": "Rhagionidae",
          "commonName": "노랑등에과",
          "ktsn": 120000022685
        },
        "genus": {
          "scientificName": "Chrysopilus",
          "commonName": "",
          "ktsn": 120000022686
        },
        "subgenus": {
          "scientificName": "",
          "commonName": "",
          "ktsn": null
        },
        "species": {
          "scientificName": "sauteri",
          "commonName": "노랑등에",
          "ktsn": 120000022687
        }
      },
      "digitalContent": {
        "cachedAt": "2026-05-21T09:17:27.013Z",
        "source": "https://species.nibr.go.kr/gwsvc/openapi/rest/digital/bispconts/search",
        "totalElements": 0,
        "totalPages": 1,
        "thumbnailUrl": null,
        "thumbnail": null,
        "contents": {
          "EO": [],
          "FR": [],
          "DT": [],
          "EX": []
        }
      },
      "eol": {
        "pageId": 821270,
        "canonical": "Chrysopilus sauteri",
        "fetchedAt": "2026-05-24T09:07:19.901Z",
        "vernaculars": {
          "ko": [
            "노랑등에"
          ],
          "en": [],
          "ja": []
        },
        "habitat": [],
        "geographic": [],
        "introduced": [],
        "eats": [],
        "visitsFlowersOf": [],
        "pathogenOf": [],
        "gbifRecords": 38
      }
    },
    {
      "ktsn": 120000225334,
      "scientificName": "Rhagio flavimedius (Coquillett, 1898)",
      "commonName": "도요노랑파리",
      "terminalLatinName": "flavimedius",
      "nomenclaturalAuthor": "",
      "namingYear": "",
      "corsynSeYn": "Y",
      "egspcsYn": "N",
      "hrmflSpecsYn": "N",
      "dispYn": "N",
      "phspYn": "N",
      "korUnqBispYn": "N",
      "ntmYn": "N",
      "taxonomy": {
        "phylum": {
          "scientificName": "Arthropoda",
          "commonName": "절지동물문",
          "ktsn": 120000013748
        },
        "class": {
          "scientificName": "Insecta",
          "commonName": "곤충강",
          "ktsn": 120000013749
        },
        "order": {
          "scientificName": "Diptera",
          "commonName": "파리목",
          "ktsn": 120000020933
        },
        "family": {
          "scientificName": "Rhagionidae",
          "commonName": "노랑등에과",
          "ktsn": 120000022685
        },
        "genus": {
          "scientificName": "Rhagio",
          "commonName": "도요노랑등에속",
          "ktsn": 120000225332
        },
        "subgenus": {
          "scientificName": "",
          "commonName": "",
          "ktsn": null
        },
        "species": {
          "scientificName": "flavimedius",
          "commonName": "도요노랑파리",
          "ktsn": 120000225334
        }
      },
      "digitalContent": {
        "cachedAt": "2026-05-21T09:17:27.013Z",
        "source": "https://species.nibr.go.kr/gwsvc/openapi/rest/digital/bispconts/search",
        "totalElements": 0,
        "totalPages": 1,
        "thumbnailUrl": null,
        "thumbnail": null,
        "contents": {
          "EO": [],
          "FR": [],
          "DT": [],
          "EX": []
        }
      },
      "eol": {
        "pageId": 819162,
        "canonical": "Rhagio flavimedius",
        "fetchedAt": "2026-05-24T09:07:26.784Z",
        "vernaculars": {
          "ko": [],
          "en": [],
          "ja": []
        },
        "habitat": [],
        "geographic": [
          "Japan"
        ],
        "introduced": [],
        "eats": [],
        "visitsFlowersOf": [],
        "pathogenOf": [],
        "gbifRecords": 47
      }
    },
    {
      "ktsn": 120000511055,
      "scientificName": "Rhagio seorsus Lee and Suh, 2022",
      "commonName": "벌난도요노랑등에",
      "terminalLatinName": "seorsus",
      "nomenclaturalAuthor": "Lee and Suh",
      "namingYear": "2022",
      "corsynSeYn": "Y",
      "egspcsYn": "N",
      "hrmflSpecsYn": "N",
      "dispYn": "N",
      "phspYn": "N",
      "korUnqBispYn": "Y",
      "ntmYn": "N",
      "taxonomy": {
        "phylum": {
          "scientificName": "Arthropoda",
          "commonName": "절지동물문",
          "ktsn": 120000013748
        },
        "class": {
          "scientificName": "Insecta",
          "commonName": "곤충강",
          "ktsn": 120000013749
        },
        "order": {
          "scientificName": "Diptera",
          "commonName": "파리목",
          "ktsn": 120000020933
        },
        "family": {
          "scientificName": "Rhagionidae",
          "commonName": "노랑등에과",
          "ktsn": 120000022685
        },
        "genus": {
          "scientificName": "Rhagio",
          "commonName": "도요노랑등에속",
          "ktsn": 120000225332
        },
        "subgenus": {
          "scientificName": "",
          "commonName": "",
          "ktsn": null
        },
        "species": {
          "scientificName": "seorsus",
          "commonName": "벌난도요노랑등에",
          "ktsn": 120000511055
        }
      },
      "digitalContent": {
        "cachedAt": "2026-05-21T09:17:27.013Z",
        "source": "https://species.nibr.go.kr/gwsvc/openapi/rest/digital/bispconts/search",
        "totalElements": 0,
        "totalPages": 1,
        "thumbnailUrl": null,
        "thumbnail": null,
        "contents": {
          "EO": [],
          "FR": [],
          "DT": [],
          "EX": []
        }
      }
    }
  ],
  "digitalContentUpdatedAt": "2026-05-21T09:17:27.013Z",
  "digitalContentSource": "https://species.nibr.go.kr/gwsvc/openapi/rest/digital/bispconts/search"
}